standpy/__init__.py
standpy/standpy.py
standpy-0.1.1.dist-info/LICENSE
standpy-0.1.1.dist-info/METADATA
standpy-0.1.1.dist-info/WHEEL
standpy-0.1.1.dist-info/top_level.txt
standpy-0.1.1.dist-info/RECORD
