Metadata-Version: 2.1
Name: standpy
Version: 0.1.1
Summary: Standby prevention module.
Home-page: UNKNOWN
Author: Pedro Maciel Xavier
Author-email: pedromxavier@poli.ufrj.br
License: UNKNOWN
Platform: UNKNOWN
Classifier: Programming Language :: Python :: 3
Requires-Python: <4,>=3.7
Requires-Dist: oswhich
